{"name":"select the product free investmnet","id":"as-a-quality-analyst;select-the-product-free-investmnet","testSteps":[{"number":1,"description":"Elkin opens the browser at https://www.cfa.com.co","duration":18868,"startTime":"2023-04-15T16:26:22.335-05:00[America/Bogota]","screenshots":[{"screenshot":"ce09dcc079f24ad640a0aed79f6eda7642f27bb1a95266316b645052a39c1440.png","timeStamp":1681594001202,"screenshotName":"ce09dcc079f24ad640a0aed79f6eda7642f27bb1a95266316b645052a39c1440.png"}],"result":"SUCCESS","precondition":false,"level":0},{"number":2,"description":"When : I see the option \"free investmnet\"","duration":26814,"startTime":"2023-04-15T16:26:41.238-05:00[America/Bogota]","screenshots":[{"screenshot":"70a89f22988f32e88ffadae257cd48dbb2741f3c3e6325c4c667e51b3f98ad11.png","timeStamp":1681594028052,"screenshotName":"70a89f22988f32e88ffadae257cd48dbb2741f3c3e6325c4c667e51b3f98ad11.png"}],"result":"SUCCESS","precondition":false,"level":0,"children":[{"number":3,"description":"Elkin credits person","duration":26763,"startTime":"2023-04-15T16:26:41.264-05:00[America/Bogota]","screenshots":[{"screenshot":"70a89f22988f32e88ffadae257cd48dbb2741f3c3e6325c4c667e51b3f98ad11.png","timeStamp":1681594028027,"screenshotName":"70a89f22988f32e88ffadae257cd48dbb2741f3c3e6325c4c667e51b3f98ad11.png"}],"result":"SUCCESS","precondition":false,"level":1,"children":[{"number":4,"description":"Elkin clicks on PRODUCT","duration":1283,"startTime":"2023-04-15T16:26:41.305-05:00[America/Bogota]","screenshots":[{"screenshot":"f54d68b80a71a441fca3408b1c0d2818bdfbc6621ede5e2086f80ca438778536.png","timeStamp":1681594002588,"screenshotName":"f54d68b80a71a441fca3408b1c0d2818bdfbc6621ede5e2086f80ca438778536.png"}],"result":"SUCCESS","precondition":false,"level":2},{"number":5,"description":"Elkin clicks on PERSONS","duration":7857,"startTime":"2023-04-15T16:26:42.593-05:00[America/Bogota]","screenshots":[{"screenshot":"44f01bbfb2916ae85d61e426c444c67377c7e1f75c2fb89fddd8f422450d74f7.png","timeStamp":1681594010449,"screenshotName":"44f01bbfb2916ae85d61e426c444c67377c7e1f75c2fb89fddd8f422450d74f7.png"}],"result":"SUCCESS","precondition":false,"level":2},{"number":6,"description":"Elkin clicks on CREDITS_OF_CONSUMPTION","duration":9009,"startTime":"2023-04-15T16:26:50.453-05:00[America/Bogota]","screenshots":[{"screenshot":"0a3e7a9aede14329a6870b2ba161d93c62eb3b7e9f3c8483e6e610e2d297105a.png","timeStamp":1681594019462,"screenshotName":"0a3e7a9aede14329a6870b2ba161d93c62eb3b7e9f3c8483e6e610e2d297105a.png"}],"result":"SUCCESS","precondition":false,"level":2},{"number":7,"description":"Elkin clicks on CREDITS_FREE_INVESTMENT","duration":4200,"startTime":"2023-04-15T16:26:59.482-05:00[America/Bogota]","screenshots":[{"screenshot":"2ad054a758d641f9c44eeb2ac930bc1b2589d1dfecd72a4ca4374cd08512003e.png","timeStamp":1681594023682,"screenshotName":"2ad054a758d641f9c44eeb2ac930bc1b2589d1dfecd72a4ca4374cd08512003e.png"}],"result":"SUCCESS","precondition":false,"level":2},{"number":8,"description":"Elkin clicks on REQUEST_PRODUCT","duration":4010,"startTime":"2023-04-15T16:27:03.698-05:00[America/Bogota]","screenshots":[{"screenshot":"30a8326acc328cbfa742a784ea590dea6e4cab877dc7c43525bbe3438f757f51.png","timeStamp":1681594027708,"screenshotName":"30a8326acc328cbfa742a784ea590dea6e4cab877dc7c43525bbe3438f757f51.png"}],"result":"SUCCESS","precondition":false,"level":2}]}]},{"number":9,"description":"Then : I see the all information \"Línea Antioquia\"","duration":528,"startTime":"2023-04-15T16:27:08.053-05:00[America/Bogota]","screenshots":[{"screenshot":"edf0d2f2eacc4bc439c4b140d8348cf92b6943fc1a3df0e9cf8fe653013071a6.png","timeStamp":1681594028581,"screenshotName":"edf0d2f2eacc4bc439c4b140d8348cf92b6943fc1a3df0e9cf8fe653013071a6.png"}],"result":"SUCCESS","precondition":false,"level":0,"children":[{"number":10,"description":"Then final message should be \u0027L\u0026iacute;nea Antioquia\u0027","duration":298,"startTime":"2023-04-15T16:27:08.254-05:00[America/Bogota]","screenshots":[{"screenshot":"edf0d2f2eacc4bc439c4b140d8348cf92b6943fc1a3df0e9cf8fe653013071a6.png","timeStamp":1681594028552,"screenshotName":"edf0d2f2eacc4bc439c4b140d8348cf92b6943fc1a3df0e9cf8fe653013071a6.png"}],"result":"SUCCESS","precondition":false,"level":1}]}],"userStory":{"id":"as-a-quality-analyst","storyName":"as a quality analyst","displayName":"as a quality analyst","path":"credits_of_person.feature","narrative":"  I want to test the selection flow of a credit product.\n  to confirm its correct operation","type":"feature"},"featureTag":{"name":"as a quality analyst","type":"feature","displayName":"as a quality analyst"},"title":"select the product free investmnet","description":"","tags":[{"name":"as a quality analyst","type":"feature","displayName":"as a quality analyst"},{"name":"FreeInvestment","type":"tag","displayName":"FreeInvestment"}],"startTime":"2023-04-15T16:26:21.782-05:00[America/Bogota]","duration":46804,"projectKey":"","sessionId":"e60b6acaf1f532d7d9493f28a02b7870","driver":"chrome","isManualTestingUpToDate":false,"manual":false,"testSource":"Cucumber","actors":[{"name":"Elkin","can":["browse the web"]}],"result":"SUCCESS"}